test_add_capability_to_project2/__init__.py
test_add_capability_to_project2-0.0.0.dist-info/METADATA
test_add_capability_to_project2-0.0.0.dist-info/WHEEL
test_add_capability_to_project2-0.0.0.dist-info/RECORD
