Metadata-Version: 2.4
Name: test_add_capability_to_project2
Version: 0.0.0
Summary: Placeholder - package coming soon
Classifier: Development Status :: 1 - Planning
Requires-Python: >=3.12
